Classfile /D:/study/ideacode/LeetCode/out/production/LeetCode/Test2.class
  Last modified 2020-8-26; size 907 bytes
  MD5 checksum 2349a176c49c6cf185d37e49bbfa96a7
  Compiled from "Test2.java"
public class Test2<T extends java.lang.Object> extends java.lang.Object
  minor version: 0
  major version: 52
  flags: ACC_PUBLIC, ACC_SUPER
Constant pool:
   #1 = Methodref          #11.#32        // java/lang/Object."<init>":()V
   #2 = Class              #33            // java/util/ArrayList
   #3 = Methodref          #2.#32         // java/util/ArrayList."<init>":()V
   #4 = String             #34            // 1
   #5 = InterfaceMethodref #35.#36        // java/util/List.add:(Ljava/lang/Object;)Z
   #6 = Fieldref           #37.#38        // java/lang/System.out:Ljava/io/PrintStream;
   #7 = InterfaceMethodref #35.#39        // java/util/List.get:(I)Ljava/lang/Object;
   #8 = Class              #40            // java/lang/String
   #9 = Methodref          #41.#42        // java/io/PrintStream.println:(Ljava/lang/String;)V
  #10 = Class              #43            // Test2
  #11 = Class              #44            // java/lang/Object
  #12 = Utf8               <init>
  #13 = Utf8               ()V
  #14 = Utf8               Code
  #15 = Utf8               LineNumberTable
  #16 = Utf8               LocalVariableTable
  #17 = Utf8               this
  #18 = Utf8               LTest2;
  #19 = Utf8               LocalVariableTypeTable
  #20 = Utf8               LTest2<TT;>;
  #21 = Utf8               main
  #22 = Utf8               ([Ljava/lang/String;)V
  #23 = Utf8               args
  #24 = Utf8               [Ljava/lang/String;
  #25 = Utf8               list
  #26 = Utf8               Ljava/util/List;
  #27 = Utf8               Ljava/util/List<Ljava/lang/String;>;
  #28 = Utf8               Signature
  #29 = Utf8               <T:Ljava/lang/Object;>Ljava/lang/Object;
  #30 = Utf8               SourceFile
  #31 = Utf8               Test2.java
  #32 = NameAndType        #12:#13        // "<init>":()V
  #33 = Utf8               java/util/ArrayList
  #34 = Utf8               1
  #35 = Class              #45            // java/util/List
  #36 = NameAndType        #46:#47        // add:(Ljava/lang/Object;)Z
  #37 = Class              #48            // java/lang/System
  #38 = NameAndType        #49:#50        // out:Ljava/io/PrintStream;
  #39 = NameAndType        #51:#52        // get:(I)Ljava/lang/Object;
  #40 = Utf8               java/lang/String
  #41 = Class              #53            // java/io/PrintStream
  #42 = NameAndType        #54:#55        // println:(Ljava/lang/String;)V
  #43 = Utf8               Test2
  #44 = Utf8               java/lang/Object
  #45 = Utf8               java/util/List
  #46 = Utf8               add
  #47 = Utf8               (Ljava/lang/Object;)Z
  #48 = Utf8               java/lang/System
  #49 = Utf8               out
  #50 = Utf8               Ljava/io/PrintStream;
  #51 = Utf8               get
  #52 = Utf8               (I)Ljava/lang/Object;
  #53 = Utf8               java/io/PrintStream
  #54 = Utf8               println
  #55 = Utf8               (Ljava/lang/String;)V
{
  public Test2();
    descriptor: ()V
    flags: ACC_PUBLIC
    Code:
      stack=1, locals=1, args_size=1
         0: aload_0
         1: invokespecial #1                  // Method java/lang/Object."<init>":()V
         4: return
      LineNumberTable:
        line 8: 0
      LocalVariableTable:
        Start  Length  Slot  Name   Signature
            0       5     0  this   LTest2;
      LocalVariableTypeTable:
        Start  Length  Slot  Name   Signature
            0       5     0  this   LTest2<TT;>;

  public static void main(java.lang.String[]);
    descriptor: ([Ljava/lang/String;)V
    flags: ACC_PUBLIC, ACC_STATIC
    Code:
      stack=3, locals=2, args_size=1
         0: new           #2                  // class java/util/ArrayList
         3: dup
         4: invokespecial #3                  // Method java/util/ArrayList."<init>":()V
         7: astore_1
         8: aload_1
         9: ldc           #4                  // String 1
        11: invokeinterface #5,  2            // InterfaceMethod java/util/List.add:(Ljava/lang/Object;)Z
        16: pop
        17: getstatic     #6                  // Field java/lang/System.out:Ljava/io/PrintStream;
        20: aload_1
        21: iconst_1
        22: invokeinterface #7,  2            // InterfaceMethod java/util/List.get:(I)Ljava/lang/Object;
        27: checkcast     #8                  // class java/lang/String
        30: invokevirtual #9                  // Method java/io/PrintStream.println:(Ljava/lang/String;)V
        33: return
      LineNumberTable:
        line 10: 0
        line 11: 8
        line 12: 17
        line 13: 33
      LocalVariableTable:
        Start  Length  Slot  Name   Signature
            0      34     0  args   [Ljava/lang/String;
            8      26     1  list   Ljava/util/List;
      LocalVariableTypeTable:
        Start  Length  Slot  Name   Signature
            8      26     1  list   Ljava/util/List<Ljava/lang/String;>;
}
Signature: #29                          // <T:Ljava/lang/Object;>Ljava/lang/Object;
SourceFile: "Test2.java"